MANIFEST.in
README.rst
setup.py
src/sentry_nirror/__init__.py
src/sentry_nirror/models.py
src/sentry_nirror/plugin.py
src/sentry_nirror.egg-info/PKG-INFO
src/sentry_nirror.egg-info/SOURCES.txt
src/sentry_nirror.egg-info/dependency_links.txt
src/sentry_nirror.egg-info/entry_points.txt
src/sentry_nirror.egg-info/not-zip-safe
src/sentry_nirror.egg-info/requires.txt
src/sentry_nirror.egg-info/top_level.txt
src/sentry_nirror/templates/widget.html