Metadata-Version: 1.1
Name: sentry-nirror
Version: 0.1.1
Summary: A Sentry extension which integrates with Nirror.
Home-page: http://github.com/nirror/sentry-nirror
Author: Tugdual de Kerviler
Author-email: dekervit@gmail.com
License: BSD
Platform: UNKNOWN
Classifier: Framework :: Django
Classifier: Intended Audience :: Developers
Classifier: Intended Audience :: System Administrators
Classifier: Operating System :: OS Independent
Classifier: Topic :: Software Development
